pycgmes/shacl/__init__.py
pycgmes/shacl/datafiles/Common/IdentifiedObjecStringLength.rdf
pycgmes/shacl/datafiles/Common/IdentifiedObjecStringLength.ttl
pycgmes/shacl/datafiles/CrossProfileValueType/DL_453_cp_explicit.rdf
pycgmes/shacl/datafiles/CrossProfileValueType/DL_453_cp_explicit.ttl
pycgmes/shacl/datafiles/CrossProfileValueType/DL_453_cp_implicit.rdf
pycgmes/shacl/datafiles/CrossProfileValueType/DL_453_cp_implicit.ttl
pycgmes/shacl/datafiles/CrossProfileValueType/DY_457_cp_explicit.rdf
pycgmes/shacl/datafiles/CrossProfileValueType/DY_457_cp_explicit.ttl
pycgmes/shacl/datafiles/CrossProfileValueType/DY_457_cp_implicit.rdf
pycgmes/shacl/datafiles/CrossProfileValueType/DY_457_cp_implicit.ttl
pycgmes/shacl/datafiles/CrossProfileValueType/GL_13_cp_explicit.rdf
pycgmes/shacl/datafiles/CrossProfileValueType/GL_13_cp_explicit.ttl
pycgmes/shacl/datafiles/CrossProfileValueType/GL_13_cp_implicit.rdf
pycgmes/shacl/datafiles/CrossProfileValueType/GL_13_cp_implicit.ttl
pycgmes/shacl/datafiles/CrossProfileValueType/OP_452_cp_explicit.rdf
pycgmes/shacl/datafiles/CrossProfileValueType/OP_452_cp_explicit.ttl
pycgmes/shacl/datafiles/CrossProfileValueType/OP_452_cp_implicit.rdf
pycgmes/shacl/datafiles/CrossProfileValueType/OP_452_cp_implicit.ttl
pycgmes/shacl/datafiles/CrossProfileValueType/SC_452_cp.rdf
pycgmes/shacl/datafiles/CrossProfileValueType/SC_452_cp.ttl
pycgmes/shacl/datafiles/CrossProfileValueType/SV_456_cp_explicit.rdf
pycgmes/shacl/datafiles/CrossProfileValueType/SV_456_cp_explicit.ttl
pycgmes/shacl/datafiles/CrossProfileValueType/SV_456_cp_implicit.rdf
pycgmes/shacl/datafiles/CrossProfileValueType/SV_456_cp_implicit.ttl
pycgmes/shacl/datafiles/CrossProfileValueType/TP_456_cp_explicit.rdf
pycgmes/shacl/datafiles/CrossProfileValueType/TP_456_cp_explicit.ttl
pycgmes/shacl/datafiles/CrossProfileValueType/TP_456_cp_implicit.rdf
pycgmes/shacl/datafiles/CrossProfileValueType/TP_456_cp_implicit.ttl
pycgmes/shacl/datafiles/DatatypeMapping/CompleteDatatypeMap.properties
pycgmes_shacl-1.0.1.dist-info/METADATA
pycgmes_shacl-1.0.1.dist-info/WHEEL
pycgmes_shacl-1.0.1.dist-info/RECORD
