Metadata-Version: 2.1
Name: pycgmes-shacl
Version: 1.0.1
Summary: Python dataclasses for CGMES 3.0.0
Home-page: https://github.com/alliander-opensource/pycgmes
License: Apache 2.0
Author: pycgmes
Author-email: pycgmes@alliander.com
Requires-Python: >=3.10,<4.0
Classifier: Development Status :: 5 - Production/Stable
Classifier: License :: OSI Approved :: Apache Software License
Classifier: License :: Other/Proprietary License
Classifier: Operating System :: OS Independent
Classifier: Programming Language :: Python :: 3
Classifier: Programming Language :: Python :: 3.10
Classifier: Programming Language :: Python :: 3.11
Classifier: Topic :: Software Development :: Libraries :: Python Modules
Classifier: Typing :: Typed
Requires-Dist: poetry (>=1.5.0)
Requires-Dist: pyshacl
Project-URL: Repository, https://github.com/alliander-opensource/pycgmes
